treat_rl/__init__.py
treat_rl/custom_metrics.py
treat_rl/data_gen.py
treat_rl/envs.py
treat_rl/policies.py
treat_rl-0.5.1.dist-info/LICENSE
treat_rl-0.5.1.dist-info/METADATA
treat_rl-0.5.1.dist-info/WHEEL
treat_rl-0.5.1.dist-info/top_level.txt
treat_rl-0.5.1.dist-info/RECORD
