Metadata-Version: 2.1
Name: treat-rl
Version: 0.5.1
License-File: LICENSE
Requires-Dist: gym
Requires-Dist: numpy
